kinglib/__init__.py
kinglib/dingtalk.py
kinglib/excel.py
kinglib/excelfile.py
kinglib/run.py
kinglib-0.1.0.dist-info/LICENSE
kinglib-0.1.0.dist-info/METADATA
kinglib-0.1.0.dist-info/WHEEL
kinglib-0.1.0.dist-info/entry_points.txt
kinglib-0.1.0.dist-info/top_level.txt
kinglib-0.1.0.dist-info/RECORD
