Metadata-Version: 2.1
Name: kinglib
Version: 0.1.0
Summary: setup kinglib
Home-page: UNKNOWN
Author: Guozhi Hu
Author-email: guozhi.hu@qq.com
License: MIT
Keywords: setup,kinglib
Platform: any
Requires-Dist: openpyxl (>=3.0.3)
Requires-Dist: xlrd (>=1.2.0)
Requires-Dist: xlwt (>=1.3.0)
